{
  "$schema": "https://developer.microsoft.com/json-schemas/fabric/item/report/definition/visualContainer/2.5.0/schema.json",
  "name": "d4e5f6a1b2c3",
  "position": {
    "x": 454.99458373544991,
    "y": 166.18596498138774,
    "z": 3000,
    "height": 161.3455970693085,
    "width": 264.60677919366594,
    "tabOrder": 3000
  },
  "visual": {
    "visualType": "lineChart",
    "query": {
      "queryState": {
        "Category": {
          "projections": [
            {
              "field": {
                "Column": {
                  "Expression": {
                    "SourceRef": {
                      "Entity": "Extract_1"
                    }
                  },
                  "Property": "Month_1"
                }
              },
              "queryRef": "Extract_1.Month_1",
              "nativeQueryRef": "Month_1",
              "active": true
            }
          ]
        },
        "Series": {
          "projections": [
            {
              "field": {
                "Column": {
                  "Expression": {
                    "SourceRef": {
                      "Entity": "Extract_1"
                    }
                  },
                  "Property": "Year"
                }
              },
              "queryRef": "Extract_1.Year",
              "nativeQueryRef": "Year"
            }
          ]
        },
        "Tooltips": {
          "projections": [
            {
              "field": {
                "Aggregation": {
                  "Expression": {
                    "Column": {
                      "Expression": {
                        "SourceRef": {
                          "Entity": "Extract_1"
                        }
                      },
                      "Property": "Count"
                    }
                  },
                  "Function": 0
                }
              },
              "queryRef": "Sum(Extract_1.Count)",
              "nativeQueryRef": "Mail Quantity",
              "displayName": "Mail Quantity"
            },
            {
              "field": {
                "Measure": {
                  "Expression": {
                    "SourceRef": {
                      "Entity": "_Measures"
                    }
                  },
                  "Property": "Cost per Call"
                }
              },
              "queryRef": "_Measures.Cost per Call",
              "nativeQueryRef": "Cost per Call"
            },
            {
              "field": {
                "Measure": {
                  "Expression": {
                    "SourceRef": {
                      "Entity": "_Measures"
                    }
                  },
                  "Property": "Resp. Rate"
                }
              },
              "queryRef": "_Measures.Resp. Rate",
              "nativeQueryRef": "Response Rate",
              "displayName": "Response Rate"
            }
          ]
        },
        "Y": {
          "projections": [
            {
              "field": {
                "Aggregation": {
                  "Expression": {
                    "Column": {
                      "Expression": {
                        "SourceRef": {
                          "Entity": "Extract_1"
                        }
                      },
                      "Property": "Total_Calls"
                    }
                  },
                  "Function": 0
                }
              },
              "queryRef": "Sum(Extract_1.Total_Calls)",
              "nativeQueryRef": "Total Calls",
              "displayName": "Total Calls"
            }
          ]
        }
      }
    },
    "objects": {
      "legend": [
        {
          "properties": {
            "show": {
              "expr": {
                "Literal": {
                  "Value": "false"
                }
              }
            },
            "position": {
              "expr": {
                "Literal": {
                  "Value": "'RightCenter'"
                }
              }
            },
            "showTitle": {
              "expr": {
                "Literal": {
                  "Value": "false"
                }
              }
            },
            "fontFamily": {
              "expr": {
                "Literal": {
                  "Value": "'Calibri'"
                }
              }
            },
            "bold": {
              "expr": {
                "Literal": {
                  "Value": "true"
                }
              }
            },
            "labelColor": {
              "solid": {
                "color": {
                  "expr": {
                    "ThemeDataColor": {
                      "ColorId": 1,
                      "Percent": 0
                    }
                  }
                }
              }
            },
            "legendMarkerRendering": {
              "expr": {
                "Literal": {
                  "Value": "'lineOnly'"
                }
              }
            }
          }
        }
      ],
      "categoryAxis": [
        {
          "properties": {
            "show": {
              "expr": {
                "Literal": {
                  "Value": "false"
                }
              }
            },
            "fontFamily": {
              "expr": {
                "Literal": {
                  "Value": "'Calibri'"
                }
              }
            },
            "bold": {
              "expr": {
                "Literal": {
                  "Value": "true"
                }
              }
            },
            "labelColor": {
              "solid": {
                "color": {
                  "expr": {
                    "Literal": {
                      "Value": "'#252423'"
                    }
                  }
                }
              }
            },
            "showAxisTitle": {
              "expr": {
                "Literal": {
                  "Value": "false"
                }
              }
            }
          }
        }
      ],
      "valueAxis": [
        {
          "properties": {
            "show": {
              "expr": {
                "Literal": {
                  "Value": "true"
                }
              }
            },
            "fontFamily": {
              "expr": {
                "Literal": {
                  "Value": "'Calibri'"
                }
              }
            },
            "bold": {
              "expr": {
                "Literal": {
                  "Value": "true"
                }
              }
            },
            "labelColor": {
              "solid": {
                "color": {
                  "expr": {
                    "ThemeDataColor": {
                      "ColorId": 1,
                      "Percent": 0
                    }
                  }
                }
              }
            },
            "labelDisplayUnits": {
              "expr": {
                "Literal": {
                  "Value": "1D"
                }
              }
            },
            "showAxisTitle": {
              "expr": {
                "Literal": {
                  "Value": "false"
                }
              }
            }
          }
        }
      ]
    },
    "visualContainerObjects": {
      "title": [
        {
          "properties": {
            "text": {
              "expr": {
                "Literal": {
                  "Value": "'Total Calls Trend'"
                }
              }
            },
            "titleWrap": {
              "expr": {
                "Literal": {
                  "Value": "true"
                }
              }
            },
            "fontSize": {
              "expr": {
                "Literal": {
                  "Value": "16D"
                }
              }
            },
            "bold": {
              "expr": {
                "Literal": {
                  "Value": "true"
                }
              }
            },
            "fontFamily": {
              "expr": {
                "Literal": {
                  "Value": "'Calibri'"
                }
              }
            }
          }
        }
      ],
      "border": [
        {
          "properties": {
            "show": {
              "expr": {
                "Literal": {
                  "Value": "true"
                }
              }
            },
            "width": {
              "expr": {
                "Literal": {
                  "Value": "1D"
                }
              }
            }
          }
        }
      ],
      "background": [
        {
          "properties": {
            "show": {
              "expr": {
                "Literal": {
                  "Value": "true"
                }
              }
            },
            "transparency": {
              "expr": {
                "Literal": {
                  "Value": "0D"
                }
              }
            }
          }
        }
      ],
      "padding": [
        {
          "properties": {
            "bottom": {
              "expr": {
                "Literal": {
                  "Value": "0D"
                }
              }
            },
            "left": {
              "expr": {
                "Literal": {
                  "Value": "0D"
                }
              }
            },
            "right": {
              "expr": {
                "Literal": {
                  "Value": "0D"
                }
              }
            }
          }
        }
      ],
      "visualTooltip": [
        {
          "properties": {
            "show": {
              "expr": {
                "Literal": {
                  "Value": "true"
                }
              }
            },
            "fontFamily": {
              "expr": {
                "Literal": {
                  "Value": "'Calibri'"
                }
              }
            }
          }
        }
      ]
    },
    "drillFilterOtherVisuals": true
  },
  "filterConfig": {
    "filters": [
      {
        "name": "1d05e102b6504e6e7e1c",
        "ordinal": 0,
        "field": {
          "Measure": {
            "Expression": {
              "SourceRef": {
                "Entity": "_Measures"
              }
            },
            "Property": "Cost per Call"
          }
        },
        "type": "Advanced"
      },
      {
        "name": "0a3db1a1f65355da8394",
        "ordinal": 1,
        "field": {
          "Aggregation": {
            "Expression": {
              "Column": {
                "Expression": {
                  "SourceRef": {
                    "Entity": "Extract_1"
                  }
                },
                "Property": "Count"
              }
            },
            "Function": 0
          }
        },
        "type": "Advanced"
      },
      {
        "name": "d48ba5b3f0979ad70fb9",
        "ordinal": 2,
        "field": {
          "Measure": {
            "Expression": {
              "SourceRef": {
                "Entity": "_Measures"
              }
            },
            "Property": "Date Range Ext1"
          }
        },
        "type": "Advanced",
        "filter": {
          "Version": 2,
          "From": [
            {
              "Name": "_",
              "Entity": "_Measures",
              "Type": 0
            }
          ],
          "Where": [
            {
              "Condition": {
                "Comparison": {
                  "ComparisonKind": 0,
                  "Left": {
                    "Measure": {
                      "Expression": {
                        "SourceRef": {
                          "Source": "_"
                        }
                      },
                      "Property": "Date Range Ext1"
                    }
                  },
                  "Right": {
                    "Literal": {
                      "Value": "1L"
                    }
                  }
                }
              }
            }
          ]
        },
        "howCreated": "User"
      },
      {
        "name": "3e39c1ebe16440dc912b",
        "ordinal": 3,
        "field": {
          "Column": {
            "Expression": {
              "SourceRef": {
                "Entity": "Extract_1"
              }
            },
            "Property": "Month_1"
          }
        },
        "type": "Categorical"
      },
      {
        "name": "343b49ee898304ca7f47",
        "ordinal": 4,
        "field": {
          "Measure": {
            "Expression": {
              "SourceRef": {
                "Entity": "_Measures"
              }
            },
            "Property": "Resp. Rate"
          }
        },
        "type": "Advanced"
      },
      {
        "name": "5cb060f22c31825e322b",
        "ordinal": 5,
        "field": {
          "Aggregation": {
            "Expression": {
              "Column": {
                "Expression": {
                  "SourceRef": {
                    "Entity": "Extract_1"
                  }
                },
                "Property": "Retailer_Cost"
              }
            },
            "Function": 0
          }
        },
        "type": "Advanced",
        "howCreated": "User"
      },
      {
        "name": "86f315cc3529de42be6b",
        "ordinal": 6,
        "field": {
          "Aggregation": {
            "Expression": {
              "Column": {
                "Expression": {
                  "SourceRef": {
                    "Entity": "Extract_1"
                  }
                },
                "Property": "Total_Calls"
              }
            },
            "Function": 0
          }
        },
        "type": "Advanced"
      },
      {
        "name": "7240ff1ec39ed8872219",
        "ordinal": 7,
        "field": {
          "Column": {
            "Expression": {
              "SourceRef": {
                "Entity": "Extract_1"
              }
            },
            "Property": "Year"
          }
        },
        "type": "Advanced"
      }
    ],
    "filterSortOrder": "Custom"
  }
}