{
  "$schema": "https://developer.microsoft.com/json-schemas/fabric/item/report/definition/visualContainer/2.5.0/schema.json",
  "name": "f6a1b2c3d4e5",
  "position": {
    "x": 1009.1416180304045,
    "y": 170.08004798265245,
    "z": 5000,
    "height": 154.96182149530554,
    "width": 262.6791852176521,
    "tabOrder": 5000
  },
  "visual": {
    "visualType": "lineChart",
    "query": {
      "queryState": {
        "Category": {
          "projections": [
            {
              "field": {
                "Column": {
                  "Expression": {
                    "SourceRef": {
                      "Entity": "Extract"
                    }
                  },
                  "Property": "Month_1"
                }
              },
              "queryRef": "Extract.Month_1",
              "nativeQueryRef": "Month_1",
              "active": true
            }
          ]
        },
        "Series": {
          "projections": [
            {
              "field": {
                "Column": {
                  "Expression": {
                    "SourceRef": {
                      "Entity": "Extract"
                    }
                  },
                  "Property": "Year"
                }
              },
              "queryRef": "Extract.Year",
              "nativeQueryRef": "Year"
            }
          ]
        },
        "Y": {
          "projections": [
            {
              "field": {
                "Aggregation": {
                  "Expression": {
                    "Column": {
                      "Expression": {
                        "SourceRef": {
                          "Entity": "Extract"
                        }
                      },
                      "Property": "DealerActivations"
                    }
                  },
                  "Function": 0
                }
              },
              "queryRef": "Sum(Extract.DealerActivations)",
              "nativeQueryRef": "Sum of DealerActivations"
            }
          ]
        }
      }
    },
    "objects": {
      "legend": [
        {
          "properties": {
            "show": {
              "expr": {
                "Literal": {
                  "Value": "false"
                }
              }
            },
            "position": {
              "expr": {
                "Literal": {
                  "Value": "'RightCenter'"
                }
              }
            },
            "showTitle": {
              "expr": {
                "Literal": {
                  "Value": "false"
                }
              }
            },
            "fontFamily": {
              "expr": {
                "Literal": {
                  "Value": "'Calibri'"
                }
              }
            },
            "bold": {
              "expr": {
                "Literal": {
                  "Value": "true"
                }
              }
            },
            "labelColor": {
              "solid": {
                "color": {
                  "expr": {
                    "ThemeDataColor": {
                      "ColorId": 1,
                      "Percent": 0
                    }
                  }
                }
              }
            },
            "legendMarkerRendering": {
              "expr": {
                "Literal": {
                  "Value": "'lineOnly'"
                }
              }
            }
          }
        }
      ],
      "categoryAxis": [
        {
          "properties": {
            "show": {
              "expr": {
                "Literal": {
                  "Value": "false"
                }
              }
            },
            "fontFamily": {
              "expr": {
                "Literal": {
                  "Value": "'Calibri'"
                }
              }
            },
            "bold": {
              "expr": {
                "Literal": {
                  "Value": "true"
                }
              }
            },
            "labelColor": {
              "solid": {
                "color": {
                  "expr": {
                    "Literal": {
                      "Value": "'#252423'"
                    }
                  }
                }
              }
            },
            "showAxisTitle": {
              "expr": {
                "Literal": {
                  "Value": "false"
                }
              }
            }
          }
        }
      ],
      "valueAxis": [
        {
          "properties": {
            "show": {
              "expr": {
                "Literal": {
                  "Value": "true"
                }
              }
            },
            "fontFamily": {
              "expr": {
                "Literal": {
                  "Value": "'Calibri'"
                }
              }
            },
            "bold": {
              "expr": {
                "Literal": {
                  "Value": "true"
                }
              }
            },
            "labelColor": {
              "solid": {
                "color": {
                  "expr": {
                    "ThemeDataColor": {
                      "ColorId": 1,
                      "Percent": 0
                    }
                  }
                }
              }
            },
            "labelDisplayUnits": {
              "expr": {
                "Literal": {
                  "Value": "1D"
                }
              }
            },
            "showAxisTitle": {
              "expr": {
                "Literal": {
                  "Value": "false"
                }
              }
            }
          }
        }
      ]
    },
    "visualContainerObjects": {
      "title": [
        {
          "properties": {
            "text": {
              "expr": {
                "Literal": {
                  "Value": "'Dealer Activations Trend'"
                }
              }
            },
            "titleWrap": {
              "expr": {
                "Literal": {
                  "Value": "true"
                }
              }
            },
            "fontSize": {
              "expr": {
                "Literal": {
                  "Value": "16D"
                }
              }
            },
            "bold": {
              "expr": {
                "Literal": {
                  "Value": "true"
                }
              }
            },
            "fontFamily": {
              "expr": {
                "Literal": {
                  "Value": "'Calibri'"
                }
              }
            }
          }
        }
      ],
      "border": [
        {
          "properties": {
            "show": {
              "expr": {
                "Literal": {
                  "Value": "true"
                }
              }
            },
            "width": {
              "expr": {
                "Literal": {
                  "Value": "1D"
                }
              }
            }
          }
        }
      ],
      "background": [
        {
          "properties": {
            "show": {
              "expr": {
                "Literal": {
                  "Value": "true"
                }
              }
            },
            "transparency": {
              "expr": {
                "Literal": {
                  "Value": "0D"
                }
              }
            }
          }
        }
      ],
      "padding": [
        {
          "properties": {
            "bottom": {
              "expr": {
                "Literal": {
                  "Value": "0D"
                }
              }
            },
            "left": {
              "expr": {
                "Literal": {
                  "Value": "0D"
                }
              }
            },
            "right": {
              "expr": {
                "Literal": {
                  "Value": "0D"
                }
              }
            }
          }
        }
      ],
      "visualTooltip": [
        {
          "properties": {
            "show": {
              "expr": {
                "Literal": {
                  "Value": "true"
                }
              }
            },
            "fontFamily": {
              "expr": {
                "Literal": {
                  "Value": "'Calibri'"
                }
              }
            }
          }
        }
      ]
    },
    "drillFilterOtherVisuals": true
  },
  "filterConfig": {
    "filters": [
      {
        "name": "ebba698c3641bbe9af3b",
        "field": {
          "Measure": {
            "Expression": {
              "SourceRef": {
                "Entity": "_Measures"
              }
            },
            "Property": "Date Range Ext"
          }
        },
        "type": "Advanced",
        "filter": {
          "Version": 2,
          "From": [
            {
              "Name": "_",
              "Entity": "_Measures",
              "Type": 0
            }
          ],
          "Where": [
            {
              "Condition": {
                "Comparison": {
                  "ComparisonKind": 0,
                  "Left": {
                    "Measure": {
                      "Expression": {
                        "SourceRef": {
                          "Source": "_"
                        }
                      },
                      "Property": "Date Range Ext"
                    }
                  },
                  "Right": {
                    "Literal": {
                      "Value": "1L"
                    }
                  }
                }
              }
            }
          ]
        },
        "howCreated": "User"
      }
    ]
  }
}